suvendu/CheckPerfectNumber.py
suvendu/Find2nd3rdmaxNumberOfListElement.py
suvendu/Find2nd3rdminOflistElement.py
suvendu/FindFactorialNumber.py
suvendu/LeapYear.py
suvendu/Magic_Matrix.py
suvendu/Matrix3D.py
suvendu/Merger_two_list.py
suvendu/NcR.py
suvendu/Number_is_Prime_or_not.py
suvendu/PalindromeNumber.py
suvendu/Perform_addition_of_two_matrix.py
suvendu/Perform_multiplication_of_two_matrix.py
suvendu/Perform_subtraction_of_two_matrix.py
suvendu/PrimeFactorOfNumber.py
suvendu/Remove_the_duplicate_data.py
suvendu/SplitTwoListEOrO.py
suvendu/StackCode.py
suvendu/__init__.py
suvendu/chkAmstrongNumber.py
suvendu/krishnamurti.py
suvendu/max_min_between_three.py
suvendu/twinprime.py
suvendu-1.1.1.dist-info/METADATA
suvendu-1.1.1.dist-info/WHEEL
suvendu-1.1.1.dist-info/top_level.txt
suvendu-1.1.1.dist-info/RECORD
