Metadata-Version: 2.1
Name: suvendu
Version: 1.1.1
Summary: Suvendu Chowdhury create this python package | Also I am a student and an enthusiastic techie.
Home-page: UNKNOWN
Author: Suvendu Chowdhury
License: UNKNOWN
Platform: UNKNOWN
